{
  "kind": "youtube#videoListResponse",
  "etag": "vIbgfiiwL21WPKHncByW7Q2M6Is",
  "items": [
    {
      "kind": "youtube#video",
      "etag": "EXGSy6PWvKQdgcDnkle8FTxvwZ8",
      "id": "JsMaIJ3nxic",
      "snippet": {
        "publishedAt": "2021-12-26T06:00:09Z",
        "channelId": "UCPGzT4wecuWM0BH9mPiulXg",
        "title": "Wizeline's 2021 Year in Review",
        "description": "A lot can happen in a year! For us, it’s been an incredible journey full of extraordinary achievements.\n\nThanks to everyone who made 2021 possible, and stay tuned — 2022 will be our biggest year yet!",
        "thumbnails": {
          "default": {
            "url": "https://i.ytimg.com/vi/JsMaIJ3nxic/default.jpg",
            "width": 120,
            "height": 90
          },
          "medium": {
            "url": "https://i.ytimg.com/vi/JsMaIJ3nxic/mqdefault.jpg",
            "width": 320,
            "height": 180
          },
          "high": {
            "url": "https://i.ytimg.com/vi/JsMaIJ3nxic/hqdefault.jpg",
            "width": 480,
            "height": 360
          },
          "standard": {
            "url": "https://i.ytimg.com/vi/JsMaIJ3nxic/sddefault.jpg",
            "width": 640,
            "height": 480
          },
          "maxres": {
            "url": "https://i.ytimg.com/vi/JsMaIJ3nxic/maxresdefault.jpg",
            "width": 1280,
            "height": 720
          }
        },
        "channelTitle": "Wizeline",
        "categoryId": "28",
        "liveBroadcastContent": "none",
        "localized": {
          "title": "Wizeline's 2021 Year in Review",
          "description": "A lot can happen in a year! For us, it’s been an incredible journey full of extraordinary achievements.\n\nThanks to everyone who made 2021 possible, and stay tuned — 2022 will be our biggest year yet!"
        }
      },
      "statistics": {
        "viewCount": "349",
        "likeCount": "24",
        "favoriteCount": "0",
        "commentCount": "0"
      }
    }
  ],
  "pageInfo": {
    "totalResults": 1,
    "resultsPerPage": 1
  }
}
